illumipy/__init__.py
illumipy/__main__.py
illumipy/appmap.yml
illumipy/classes/__init__.py
illumipy/classes/base_classes.py
illumipy/classes/illumination.py
illumipy/data.py
illumipy/defaults.py
illumipy-1.4.26.dist-info/LICENSE
illumipy-1.4.26.dist-info/METADATA
illumipy-1.4.26.dist-info/WHEEL
illumipy-1.4.26.dist-info/RECORD
