Metadata-Version: 2.1
Name: illumipy
Version: 1.4.26
Summary: illumipy is a Python module for estimating outside Illumination levels for given location, date and time.
Home-page: https://github.com/duckwilliam/illumipy
License: MIT
Keywords: solar,illumination,sun,sunrise,sunset,sunlight,sunrise-sunset,OpenWeatherMap,brightness,light
Author: Kalle Fornia
Author-email: kallefornia@tuta.io
Requires-Python: >=3.11,<4.0
Classifier: License :: OSI Approved :: MIT License
Classifier: Programming Language :: Python :: 3
Classifier: Programming Language :: Python :: 3.11
Requires-Dist: argparse (>=1.4.0,<2.0.0)
Requires-Dist: datetime (>=5.2,<6.0)
Requires-Dist: requests (>=2.31.0,<3.0.0)
Project-URL: Repository, https://github.com/duckwilliam/illumipy
